classcore/__init__.py
classcore/decorators.py
classcore/exceptions.py
classcore/factories.py
classcore/nomina.py
classcore/py.typed
classcore/utilities.py
classcore/__/__init__.py
classcore/__/doctab.py
classcore/__/imports.py
classcore/__/nomina.py
classcore/standard/__.py
classcore/standard/__init__.py
classcore/standard/behaviors.py
classcore/standard/classes.py
classcore/standard/decorators.py
classcore/standard/dynadoc.py
classcore/standard/modules.py
classcore/standard/nomina.py
classcore-1.10.dist-info/METADATA
classcore-1.10.dist-info/WHEEL
classcore-1.10.dist-info/licenses/LICENSE.txt
classcore-1.10.dist-info/RECORD
